{
    "title": "Argemone Mexicana",
    "main_image": "231.webp",
    "Common name": "Darudi",
    "Botanical Name": "Argemone Mexicana",
    "Vernacular name": "English-Mexican poppy <br/>Sanskrit-Katuparni <br/>",
    "Family": "Poppieceae" ,
"Class": "Magnoliopsida" ,
"Parts of plant used": "Seed" ,
"Chemical Constituents": "Alkaloids berberine, protopine and allocryptopine " ,
"Therapeutic uses": "Used as Painkiller, diuretic, cholagogue and anti-inflammatory,seed oil and leaf infusions are drunk to relieve cough." 
}